napalm_opengear/__init__.py
napalm_opengear/opengear.py
napalm_opengear/utils/textfsm_templates/show_arp.tpl
napalm_opengear-0.3.6.dist-info/AUTHORS
napalm_opengear-0.3.6.dist-info/LICENSE
napalm_opengear-0.3.6.dist-info/METADATA
napalm_opengear-0.3.6.dist-info/WHEEL
napalm_opengear-0.3.6.dist-info/top_level.txt
napalm_opengear-0.3.6.dist-info/RECORD
