Metadata-Version: 2.1
Name: napalm-opengear
Version: 0.3.6
Summary: NAPALM driver for OpenGear Linux
Home-page: https://github.com/yeled/napalm-opengear
Author: Charlie Allom
Author-email: charlie@evilforbeginners.com
License: UNKNOWN
Platform: UNKNOWN
Classifier: Topic :: Utilities
Classifier: Programming Language :: Python
Classifier: Programming Language :: Python :: 2
Classifier: Programming Language :: Python :: 2.7
Classifier: Programming Language :: Python :: 3
Classifier: Programming Language :: Python :: 3.7
Classifier: Operating System :: POSIX :: Linux
Classifier: Operating System :: Microsoft :: Windows
Classifier: Operating System :: MacOS
License-File: LICENSE
License-File: AUTHORS
Requires-Dist: napalm (>=2.0.0)
